pdf2doi/__init__.py
pdf2doi/config.py
pdf2doi/find_title_via_pymupdf.py
pdf2doi/finders.py
pdf2doi/main.py
pdf2doi/patterns.py
pdf2doi/test_patterns.py
pdf2doi/utils_registry.py
pdf2doi-1.7.dist-info/METADATA
pdf2doi-1.7.dist-info/WHEEL
pdf2doi-1.7.dist-info/entry_points.txt
pdf2doi-1.7.dist-info/top_level.txt
pdf2doi-1.7.dist-info/RECORD
