Metadata-Version: 2.1
Name: pdf2doi
Version: 1.7
Summary: A  python library/command-line tool to extract the DOI or other identifiers of a scientific paper from a pdf file.
Home-page: https://github.com/MicheleCotrufo/pdf2doi
Author: Michele Cotrufo
Author-email: michele.cotrufo@gmail.com
License: MIT
Platform: UNKNOWN
